atpp.py
setup.py
atpp.egg-info/PKG-INFO
atpp.egg-info/SOURCES.txt
atpp.egg-info/dependency_links.txt
atpp.egg-info/top_level.txt