Metadata-Version: 1.0
Name: atpp
Version: 1.6.6
Summary: atpp tcp protocol
Home-page: http://www.secken.com
Author: Secken
Author-email: UNKNOWN
License: LGPL
Platform: UNKNOWN
